ddginternal-0.1.2.dist-info/METADATA
ddginternal-0.1.2.dist-info/WHEEL
ddginternal/ddginternal.pyi
ddginternal/primp.pyi
ddginternal/py.typed
ddginternal/primp.py
ddginternal/exceptions.py
ddginternal/utils.py
ddginternal/__init__.py
ddginternal/core.py
ddginternal/modules.py
ddginternal/ddginternal.cpython-38-x86_64-linux-gnu.so
ddginternal-0.1.2.dist-info/RECORD
