Metadata-Version: 2.3
Name: ddginternal
Version: 0.1.2
Classifier: Programming Language :: Rust
Classifier: Programming Language :: Python :: Implementation :: CPython
Classifier: Programming Language :: Python :: Implementation :: PyPy
Requires-Dist: primp
Requires-Dist: pytest ; extra == 'tests'
Provides-Extra: tests
Summary: Duckduckgo search, into the internal API.
Requires-Python: >=3.8
Project-URL: Homepage, https://github.com/AWeirdDev/ddgsearch
Project-URL: Bug Tracker, https://github.com/AWeirdDev/ddgsearch/issues
